exm/__init__.py
exm/__main__.py
exm/const.py
exm/exm.py
exm/sections/__init__.py
exm/sections/env.py
exm/sections/java.py
exm/sections/maven.py
exm/utils/__init__.py
exm/utils/expression.py
exm/utils/yaml_util.py
exm-0.0.5.dist-info/LICENSE
exm-0.0.5.dist-info/METADATA
exm-0.0.5.dist-info/WHEEL
exm-0.0.5.dist-info/entry_points.txt
exm-0.0.5.dist-info/top_level.txt
exm-0.0.5.dist-info/RECORD
