Metadata-Version: 2.1
Name: exm
Version: 0.0.5
Summary: A tool for execution environment management
Home-page: https://github.com/darklee/exm.git
Author: DarkLee
Author-email: darklee@tenonx.com
License: UNKNOWN
Platform: UNKNOWN
Classifier: Programming Language :: Python :: 3
Classifier: License :: OSI Approved :: MIT License
Classifier: Operating System :: OS Independent
Requires-Python: >=3.8
